skosprovider_getty/__init__.py
skosprovider_getty/providers.py
skosprovider_getty/utils.py
skosprovider_getty-1.3.1.dist-info/METADATA
skosprovider_getty-1.3.1.dist-info/WHEEL
skosprovider_getty-1.3.1.dist-info/licenses/LICENSE
skosprovider_getty-1.3.1.dist-info/RECORD
